MANIFEST.in
README.rst
setup.cfg
setup.py
dreamtools/__init__.py
dreamtools.egg-info/PKG-INFO
dreamtools.egg-info/SOURCES.txt
dreamtools.egg-info/dependency_links.txt
dreamtools.egg-info/entry_points.txt
dreamtools.egg-info/not-zip-safe
dreamtools.egg-info/requires.txt
dreamtools.egg-info/top_level.txt
dreamtools/admin/__init__.py
dreamtools/admin/download_data.py
dreamtools/admin/release.py
dreamtools/core/README.rst
dreamtools/core/__init__.py
dreamtools/core/challenge.py
dreamtools/core/cindex.py
dreamtools/core/downloader.py
dreamtools/core/layout.py
dreamtools/core/rocs.py
dreamtools/core/rtools.py
dreamtools/core/sageutils.py
dreamtools/core/scoring.py
dreamtools/core/settings.py
dreamtools/core/wikitools.py
dreamtools/core/ziptools.py
dreamtools/dream10/README.rst
dreamtools/dream10/__init__.py
dreamtools/dream10/D10C1/__init__.py
dreamtools/dream10/D10C2/__init__.py
dreamtools/dream10/D10C3/__init__.py
dreamtools/dream2/README.rst
dreamtools/dream2/__init__.py
dreamtools/dream2/D2C1/README.rst
dreamtools/dream2/D2C1/__init__.py
dreamtools/dream2/D2C1/scoring.py
dreamtools/dream2/D2C1/data/BCL6_targets_and_decoys.xls
dreamtools/dream2/D2C1/data/FromNumbersToGeneNames.txt
dreamtools/dream2/D2C1/goldstandard/D2C1_goldstandard.tsv
dreamtools/dream2/D2C1/goldstandard/GoldStandard_with_AffyIds.xls
dreamtools/dream2/D2C1/leaderboard/D2C1_leaderboard.csv
dreamtools/dream2/D2C1/leaderboard/__init__.py
dreamtools/dream2/D2C1/templates/D2C1_template.tsv
dreamtools/dream2/D2C2/README.rst
dreamtools/dream2/D2C2/__init__.py
dreamtools/dream2/D2C2/scoring.py
dreamtools/dream2/D2C2/data/FromNumbersToGeneNames.txt
dreamtools/dream2/D2C2/data/INFO.txt
dreamtools/dream2/D2C2/data/Prot-Prot_Genes.xls
dreamtools/dream2/D2C2/goldstandard/D2C2_goldstandard.txt
dreamtools/dream2/D2C2/goldstandard/GoldStandard_ProtProtSubnet.txt
dreamtools/dream2/D2C2/leaderboard/D2C2_leaderboard.csv
dreamtools/dream2/D2C2/leaderboard/__init__.py
dreamtools/dream2/D2C2/templates/D2C2_template.txt
dreamtools/dream2/D2C3/README.rst
dreamtools/dream2/D2C3/__init__.py
dreamtools/dream2/D2C3/scoring.py
dreamtools/dream2/D2C3/data/FiveGene_chip.xls
dreamtools/dream2/D2C3/data/FiveGene_qPCR.xls
dreamtools/dream2/D2C3/data/INFO.txt
