Metadata-Version: 1.1
Name: dreamtools
Version: 1.2.5
Summary: Scoring functions for the DREAM / SAGE challenges
Home-page: ['https://github.com/dreamtools/dreamtools']
Author: Thomas Cokelaer
Author-email: cokelaer@gmail.com
License: BSD
Download-URL: ['http://pypi.python.org/pypi/dreamtools']
Keywords: DREAM challenges,DREAM,System Biology,Leaderboard,ROC,scoring,synapse,statistics
Platform: Linux
Platform: Unix
Platform: MacOsX
Platform: Windows
Classifier: Development Status :: 5 - Production/Stable
Classifier: Intended Audience :: Developers
Classifier: Intended Audience :: Science/Research
Classifier: License :: OSI Approved :: BSD License
Classifier: Operating System :: OS Independent
Classifier: Programming Language :: Python :: 2.7
Classifier: Topic :: Software Development :: Libraries :: Python Modules
Classifier: Topic :: Scientific/Engineering :: Bio-Informatics
Classifier: Topic :: Scientific/Engineering :: Information Analysis
Classifier: Topic :: Scientific/Engineering :: Mathematics
Classifier: Topic :: Scientific/Engineering :: Physics
